<customrecordtype scriptid="customrecord_rsm_courier_service">
  <accesstype>NONENEEDED</accesstype>
  <allowattachments>F</allowattachments>
  <allowinlinedeleting>T</allowinlinedeleting>
  <allowinlinedetaching>T</allowinlinedetaching>
  <allowinlineediting>T</allowinlineediting>
  <allowmobileaccess>F</allowmobileaccess>
  <allownumberingoverride>F</allownumberingoverride>
  <allowquickadd>T</allowquickadd>
  <allowquicksearch>F</allowquicksearch>
  <allowuiaccess>T</allowuiaccess>
  <customsegment></customsegment>
  <description></description>
  <enabledle>T</enabledle>
  <enablekeywords>T</enablekeywords>
  <enablemailmerge>F</enablemailmerge>
  <enablenametranslation>F</enablenametranslation>
  <enablenumbering>F</enablenumbering>
  <enableoptimisticlocking>T</enableoptimisticlocking>
  <enablesystemnotes>T</enablesystemnotes>
  <hierarchical>F</hierarchical>
  <icon></icon>
  <iconbuiltin>T</iconbuiltin>
  <iconindex></iconindex>
  <includeinsearchmenu>T</includeinsearchmenu>
  <includename>T</includename>
  <isinactive>F</isinactive>
  <isordered>F</isordered>
  <numberinginit></numberinginit>
  <numberingmindigits></numberingmindigits>
  <numberingprefix></numberingprefix>
  <numberingsuffix></numberingsuffix>
  <recordname>RSM : Courier service</recordname>
  <showcreationdate>F</showcreationdate>
  <showcreationdateonlist>F</showcreationdateonlist>
  <showid>F</showid>
  <showlastmodified>F</showlastmodified>
  <showlastmodifiedonlist>F</showlastmodifiedonlist>
  <shownotes>F</shownotes>
  <showowner>F</showowner>
  <showownerallowchange>F</showownerallowchange>
  <showowneronlist>F</showowneronlist>
  <customrecordcustomfields>
    <customrecordcustomfield scriptid="custrecord_rsm_courier_desc">
      <accesslevel>2</accesslevel>
      <allowquickadd>F</allowquickadd>
      <applyformatting>F</applyformatting>
      <checkspelling>F</checkspelling>
      <defaultchecked>F</defaultchecked>
      <defaultselection></defaultselection>
      <defaultvalue></defaultvalue>
      <description>Naziv kurirske službe.</description>
      <displayheight></displayheight>
      <displaytype>NORMAL</displaytype>
      <displaywidth></displaywidth>
      <dynamicdefault></dynamicdefault>
      <encryptatrest>F</encryptatrest>
      <fieldtype>TEXT</fieldtype>
      <globalsearch>F</globalsearch>
      <help></help>
      <isformula>F</isformula>
      <ismandatory>F</ismandatory>
      <isparent>F</isparent>
      <label>Naziv kurirske službe</label>
      <linktext></linktext>
      <maxlength></maxlength>
      <maxvalue></maxvalue>
      <minvalue></minvalue>
      <onparentdelete></onparentdelete>
      <parentsubtab></parentsubtab>
      <rolerestrict>F</rolerestrict>
      <searchcomparefield></searchcomparefield>
      <searchdefault></searchdefault>
      <searchlevel>2</searchlevel>
      <selectrecordtype></selectrecordtype>
      <showinlist>T</showinlist>
      <sourcefilterby></sourcefilterby>
      <sourcefrom></sourcefrom>
      <sourcelist></sourcelist>
      <storevalue>T</storevalue>
      <subtab></subtab>
    </customrecordcustomfield>
    <customrecordcustomfield scriptid="custrecord_rsm_courier_vendor">
      <accesslevel>2</accesslevel>
      <allowquickadd>F</allowquickadd>
      <applyformatting>F</applyformatting>
      <checkspelling>F</checkspelling>
      <defaultchecked>F</defaultchecked>
      <defaultselection></defaultselection>
      <defaultvalue></defaultvalue>
      <description>Oznaka kurirske službe u šifarniku dobavljača.</description>
      <displayheight></displayheight>
      <displaytype>NORMAL</displaytype>
      <displaywidth></displaywidth>
      <dynamicdefault></dynamicdefault>
      <encryptatrest>F</encryptatrest>
      <fieldtype>SELECT</fieldtype>
      <globalsearch>F</globalsearch>
      <help></help>
      <isformula>F</isformula>
      <ismandatory>F</ismandatory>
      <isparent>T</isparent>
      <label>Dobavljač</label>
      <linktext></linktext>
      <maxlength></maxlength>
      <maxvalue></maxvalue>
      <minvalue></minvalue>
      <onparentdelete>SET_NULL</onparentdelete>
      <parentsubtab></parentsubtab>
      <rolerestrict>F</rolerestrict>
      <searchcomparefield></searchcomparefield>
      <searchdefault></searchdefault>
      <searchlevel>2</searchlevel>
      <selectrecordtype>-3</selectrecordtype>
      <showinlist>T</showinlist>
      <sourcefilterby></sourcefilterby>
      <sourcefrom></sourcefrom>
      <sourcelist></sourcelist>
      <storevalue>T</storevalue>
      <subtab></subtab>
    </customrecordcustomfield>
  </customrecordcustomfields>
  <links>
    <link>
      <linkcategory>BASICLISTSRELATIONSHIPS</linkcategory>
      <linklabel>Courier services</linklabel>
      <linktasktype>LIST</linktasktype>
    </link>
  </links>
</customrecordtype>